pydantic_evals/__init__.py
pydantic_evals/_utils.py
pydantic_evals/dataset.py
pydantic_evals/generation.py
pydantic_evals/py.typed
pydantic_evals/evaluators/__init__.py
pydantic_evals/evaluators/_run_evaluator.py
pydantic_evals/evaluators/common.py
pydantic_evals/evaluators/context.py
pydantic_evals/evaluators/evaluator.py
pydantic_evals/evaluators/llm_as_a_judge.py
pydantic_evals/evaluators/spec.py
pydantic_evals/otel/__init__.py
pydantic_evals/otel/_context_in_memory_span_exporter.py
pydantic_evals/otel/_context_subtree.py
pydantic_evals/otel/_errors.py
pydantic_evals/otel/span_tree.py
pydantic_evals/reporting/__init__.py
pydantic_evals/reporting/render_numbers.py
pydantic_evals-1.50.0.dist-info/METADATA
pydantic_evals-1.50.0.dist-info/WHEEL
pydantic_evals-1.50.0.dist-info/licenses/LICENSE
pydantic_evals-1.50.0.dist-info/RECORD
